xylem/Aggregator.py
xylem/BaseComponent.py
xylem/Consumer.py
xylem/Controller.py
xylem/Core.py
xylem/EventHandler.py
xylem/Log.py
xylem/Producer.py
xylem/__init__.py
xylem/common.py
xylem/protocol.py
xylem/serialization/DictFormat.py
xylem/serialization/JSONFormat.py
xylem/serialization/__init__.py
xylem_daq-0.3.2.dist-info/METADATA
xylem_daq-0.3.2.dist-info/WHEEL
xylem_daq-0.3.2.dist-info/top_level.txt
xylem_daq-0.3.2.dist-info/RECORD
