Metadata-Version: 2.1
Name: xylem-daq
Version: 0.3.2
Summary: Modular DAQ system
Home-page: https://github.com/samkohn/xylem
Author: Sam Kohn
Author-email: skohn@lbl.gov
License: UNKNOWN
Keywords: daq physics
Platform: UNKNOWN
Requires-Dist: pyzmq
Requires-Dist: eventlet (>=0.24)
